{
  "Hotels": [
    {
      "id": 0,
      "name": "Avari Hotel",
      "web": "https://visitlahore.com/hotels/avari-hotel/",
      "description": "A mouth-watering honest Hotel",

      "addresses": [
        {
          "addressId": 0,
          "number": "75",
          "line1": "Venn Street",
          "line2": "Clapham",
          "postcode": "SW4 0BD",
          "country": "Pakistan"
        }
      ]
    },
    {
      "id": 1,
      "name": "Pipe Line Hotel",
      "web": "www.pipelinehotel.com",
      "description": "Luxury Hotel",
      "addresses": [
        {
          "addressId": 0,
          "number": "104",
          "line1": "Brick Lane",
          "line2": "Shoreditch",
          "postcode": "E1 6RL",
          "country": "Pakistan"
        }
      ]
    }
  ]
}
